__init__.py
classes.py
tle.py
orbiting-0.4.dist-info/METADATA
orbiting-0.4.dist-info/WHEEL
orbiting-0.4.dist-info/top_level.txt
orbiting-0.4.dist-info/RECORD
