Metadata-Version: 2.1
Name: orbiting
Version: 0.4
Summary: Combines Celestrak.org with a reverse-gecoder
Home-page: https://github.com/la-reine-c/Orbital
Author: Lawrence Carter
Author-email: lawrence.tn.carter@gmail.com
Requires-Dist: requests
Requires-Dist: pandas
Requires-Dist: ephem
Requires-Dist: country-converter
